Metadata-Version: 1.2
Name: django-graphql-jwt-reload
Version: 1.3.3
Summary: JSON Web Token for Django GraphQL
Home-page: https://github.com/flavors/django-graphql-jwt
Author: mongkok
Author-email: domake.io@gmail.com
Maintainer: mongkok
License: MIT
Project-URL: Documentation, https://django-graphql-jwt.domake.io
Project-URL: Issues, https://github.com/flavors/django-graphql-jwt/issues
Platform: UNKNOWN
Classifier: Development Status :: 4 - Beta
Classifier: Environment :: Web Environment
Classifier: Intended Audience :: Developers
Classifier: License :: OSI Approved :: MIT License
Classifier: Operating System :: OS Independent
Classifier: Programming Language :: Python
Classifier: Programming Language :: Python :: 3
Classifier: Programming Language :: Python :: 3.6
Classifier: Programming Language :: Python :: 3.7
Classifier: Programming Language :: Python :: 3.8
Classifier: Framework :: Django
Classifier: Framework :: Django :: 1.11
Classifier: Framework :: Django :: 2.0
Classifier: Framework :: Django :: 2.1
Classifier: Framework :: Django :: 2.2
Classifier: Framework :: Django :: 3.0
